movoid_robot_ride/__init__.py
movoid_robot_ride/desktop.py
movoid_robot_ride/shortcut.py
movoid_robotframework_ride-1.0.2.dist-info/METADATA
movoid_robotframework_ride-1.0.2.dist-info/WHEEL
movoid_robotframework_ride-1.0.2.dist-info/top_level.txt
movoid_robotframework_ride-1.0.2.dist-info/RECORD
