Metadata-Version: 2.1
Name: movoid_robotframework_ride
Version: 1.0.2
Home-page: 
Author: movoid
Author-email: bobrobotsun@163.com
Requires-Dist: robotframework-ride
